LICENSE
MANIFEST.in
README.rst
setup.py
django_mapistration.egg-info/PKG-INFO
django_mapistration.egg-info/SOURCES.txt
django_mapistration.egg-info/dependency_links.txt
django_mapistration.egg-info/not-zip-safe
django_mapistration.egg-info/requires.txt
django_mapistration.egg-info/top_level.txt
mapistration/__init__.py
mapistration/forms.py
mapistration/models.py
mapistration/templates/maps