Metadata-Version: 1.0
Name: django-mapistration
Version: 0.5
Summary: Map integration with registration form
Home-page: https://github.com/iamkhush/django-mapistration
Author: iamkhush
Author-email: ankush.chadda@gmail.com
License: UNKNOWN
Platform: UNKNOWN
Classifier: Development Status :: 4 - Beta
Classifier: Environment :: Web Environment
Classifier: Framework :: Django
Classifier: Intended Audience :: Developers
Classifier: License :: OSI Approved :: BSD License
Classifier: Operating System :: OS Independent
Classifier: Programming Language :: Python
Classifier: Topic :: Utilities
